fabrictestbed/__init__.py
fabrictestbed/fabric_manager.py
fabrictestbed/cli/__init__.py
fabrictestbed/cli/cli.py
fabrictestbed/cli/exceptions.py
fabrictestbed/external_api/__init__.py
fabrictestbed/external_api/artifact_manager.py
fabrictestbed/external_api/core_api.py
fabrictestbed/slice_editor/__init__.py
fabrictestbed/slice_manager/__init__.py
fabrictestbed/slice_manager/slice_manager.py
fabrictestbed/token_manager/__init__.py
fabrictestbed/token_manager/token_manager.py
fabrictestbed/util/__init__.py
fabrictestbed/util/constants.py
fabrictestbed/util/utils.py
fabrictestbed-1.9.1.dist-info/entry_points.txt
fabrictestbed-1.9.1.dist-info/licenses/LICENSE
fabrictestbed-1.9.1.dist-info/WHEEL
fabrictestbed-1.9.1.dist-info/METADATA
fabrictestbed-1.9.1.dist-info/RECORD
