Metadata-Version: 2.4
Name: fabrictestbed
Version: 1.9.1
Summary: FABRIC Python Client Library with CLI
Keywords: Swagger,FABRIC Python Client Library with CLI
Author-email: Komal Thareja <kthare10@renci.org>
Requires-Python: >=3.9
Classifier: Programming Language :: Python :: 3
Classifier: License :: OSI Approved :: MIT License
Classifier: Operating System :: OS Independent
License-File: LICENSE
Requires-Dist: fabric_fss_utils>=1.5.1
Requires-Dist: click
Requires-Dist: fabric-credmgr-client==1.6.2
Requires-Dist: fabric-orchestrator-client==1.9.1
Requires-Dist: paramiko
Requires-Dist: coverage>=4.0.3 ; extra == "test"
Requires-Dist: nose>=1.3.7 ; extra == "test"
Requires-Dist: pluggy>=0.3.1 ; extra == "test"
Requires-Dist: py>=1.4.31 ; extra == "test"
Requires-Dist: randomize>=0.13 ; extra == "test"
Project-URL: Home, https://fabric-testbed.net/
Project-URL: Sources, https://github.com/fabric-testbed/fabric-cli
Provides-Extra: test
